{
  "countries": {
    "Canada": {
      "country": "Canada",
      "last_24h": 51,
      "last_7d": 266,
      "last_30d": 792,
      "remote": 795,
      "on_site": 0,
      "job_listings": [
        {
          "title": "Business Intelligence Data Specialist (A25)",
          "company": "Unknown Company",
          "skills": [],
          "link": ""
        },
        {
          "title": "Senior Business Analyst",
          "company": "Unknown Company",
          "skills": [],
          "link": ""
        },
        {
          "title": "Senior Data Analyst",
          "company": "Unknown Company",
          "skills": [],
          "link": ""
        },
        {
          "title": "Business Analyst",
          "company": "Unknown Company",
          "skills": [],
          "link": ""
        },
        {
          "title": "Credit Analyst - Business Banking",
          "company": "Unknown Company",
          "skills": [],
          "link": ""
        },
        {
          "title": "Business Analyst",
          "company": "Unknown Company",
          "skills": [],
          "link": ""
        },
        {
          "title": "IT Application Analyst",
          "company": "Unknown Company",
          "skills": [],
          "link": ""
        },
        {
          "title": "IT Business Sr Analyst",
          "company": "Unknown Company",
          "skills": [],
          "link": ""
        },
        {
          "title": "Data Analyst (Canada)",
          "company": "Unknown Company",
          "skills": [],
          "link": ""
        },
        {
          "title": "Analyst, Customer Insights",
          "company": "Unknown Company",
          "skills": [],
          "link": ""
        },
        {
          "title": "Integrity Analyst - Hiring Day May 13, 2025",
          "company": "Unknown Company",
          "skills": [],
          "link": ""
        },
        {
          "title": "Summer Data Analyst",
          "company": "Unknown Company",
          "skills": [],
          "link": ""
        },
        {
          "title": "Power BI Developer",
          "company": "Unknown Company",
          "skills": [],
          "link": ""
        },
        {
          "title": "ERP Data Analyst Co-op (Onsite) - September 2025",
          "company": "Unknown Company",
          "skills": [],
          "link": ""
        },
        {
          "title": "Business Analyst and Technology Implementation Specialist - Casual",
          "company": "Unknown Company",
          "skills": [],
          "link": ""
        },
        {
          "title": "Senior Analyst Business Intelligence",
          "company": "Unknown Company",
          "skills": [],
          "link": ""
        },
        {
          "title": "Senior Business Systems Analyst",
          "company": "Unknown Company",
          "skills": [],
          "link": ""
        },
        {
          "title": "Business Development Analyst",
          "company": "Unknown Company",
          "skills": [],
          "link": ""
        },
        {
          "title": "Direct Fulfillment Analyst",
          "company": "Unknown Company",
          "skills": [],
          "link": ""
        },
        {
          "title": "Data Analyst, Delco Logistics Analytics",
          "company": "Unknown Company",
          "skills": [],
          "link": ""
        }
      ]
    },
    "Ireland": {
      "country": "Ireland",
      "last_24h": 9,
      "last_7d": 29,
      "last_30d": 112,
      "remote": 76,
      "on_site": 36,
      "job_listings": [
        {
          "title": "Productivity Analyst",
          "company": "Unknown Company",
          "skills": [
            "Power BI",
            "Business"
          ],
          "link": ""
        },
        {
          "title": "Reference Data & Quality, Associate Analyst",
          "company": "Unknown Company",
          "skills": [
            "Power BI",
            "Business"
          ],
          "link": ""
        },
        {
          "title": "Principal Product Analyst",
          "company": "Unknown Company",
          "skills": [
            "Power BI",
            "Business"
          ],
          "link": ""
        },
        {
          "title": "Sr Data Analyst",
          "company": "Unknown Company",
          "skills": [
            "Power BI",
            "Business"
          ],
          "link": ""
        },
        {
          "title": "Senior Analyst, Risk Management",
          "company": "Unknown Company",
          "skills": [
            "Power BI",
            "Business"
          ],
          "link": ""
        },
        {
          "title": "Senior Data Analytics Manager, Product",
          "company": "Unknown Company",
          "skills": [
            "Power BI",
            "Business"
          ],
          "link": ""
        },
        {
          "title": "Benefits Analyst, EMEA",
          "company": "Unknown Company",
          "skills": [
            "Power BI",
            "Business"
          ],
          "link": ""
        },
        {
          "title": "Developer (Business Intelligence/SQL)",
          "company": "Unknown Company",
          "skills": [
            "Power BI",
            "Business"
          ],
          "link": ""
        },
        {
          "title": "Senior Compensation Analyst, EMEA",
          "company": "Unknown Company",
          "skills": [
            "Power BI",
            "Business"
          ],
          "link": ""
        }
      ]
    },
    "Portugal": {
      "country": "Portugal",
      "last_24h": 2,
      "last_7d": 57,
      "last_30d": 295,
      "remote": 192,
      "on_site": 103,
      "job_listings": [
        {
          "title": "Quality Control Supervisor",
          "company": "Unknown Company",
          "skills": [],
          "link": ""
        },
        {
          "title": "Global Manufacturing Finance Analyst",
          "company": "Unknown Company",
          "skills": [],
          "link": ""
        },
        {
          "title": "Summer Internships | Data Engineer Trainee (m/f/d)",
          "company": "Unknown Company",
          "skills": [],
          "link": ""
        },
        {
          "title": "Medical writer life science",
          "company": "Unknown Company",
          "skills": [],
          "link": ""
        },
        {
          "title": "Junior Data Analyst",
          "company": "Unknown Company",
          "skills": [],
          "link": ""
        },
        {
          "title": "Portuguese Internet Search Quality Rater",
          "company": "Unknown Company",
          "skills": [],
          "link": ""
        },
        {
          "title": "Data Science Mastermind",
          "company": "Unknown Company",
          "skills": [],
          "link": ""
        }
      ]
    },
    "United Arab Emirates": {
      "country": "United Arab Emirates",
      "last_24h": 6,
      "last_7d": 31,
      "last_30d": 111,
      "remote": 11,
      "on_site": 100,
      "job_listings": [
        {
          "title": "Analyst",
          "company": "Unknown Company",
          "skills": [
            "Business"
          ],
          "link": ""
        },
        {
          "title": "SOURCING SPECIALIST - FOOD",
          "company": "Unknown Company",
          "skills": [
            "Business"
          ],
          "link": ""
        },
        {
          "title": "Pricing Analyst, Project Operations",
          "company": "Unknown Company",
          "skills": [
            "Business"
          ],
          "link": ""
        },
        {
          "title": "Consumer And Shopper Understanding Analyst, Gulf & Arab Countries",
          "company": "Unknown Company",
          "skills": [
            "Business"
          ],
          "link": ""
        },
        {
          "title": "Senior Manager \u2013 ATM and CDM",
          "company": "Unknown Company",
          "skills": [
            "Business"
          ],
          "link": ""
        },
        {
          "title": "Senior Manager \u2013 ATM and CDM",
          "company": "Unknown Company",
          "skills": [
            "Business"
          ],
          "link": ""
        }
      ]
    },
    "Germany": {
      "country": "Germany",
      "last_24h": 22,
      "last_7d": 83,
      "last_30d": 413,
      "remote": 275,
      "on_site": 138,
      "job_listings": [
        {
          "title": "Data Analyst (Gaming) (f/m/d)",
          "company": "Unknown Company",
          "skills": [
            "A/B Testing",
            "Teams",
            "Data Science"
          ],
          "link": ""
        },
        {
          "title": "Service Innovation & Strategy - BI Analyst (m/f/d) - parttime",
          "company": "Unknown Company",
          "skills": [
            "A/B Testing",
            "Teams",
            "Data Science"
          ],
          "link": ""
        },
        {
          "title": "Karrierestart als Data Analyst (m/w/d) mit KI & SQL - 100 % Online",
          "company": "Unknown Company",
          "skills": [
            "A/B Testing",
            "Teams",
            "Data Science"
          ],
          "link": ""
        },
        {
          "title": "Senior Analytics Engineer - Data Generalist (all genders)",
          "company": "Unknown Company",
          "skills": [
            "A/B Testing",
            "Teams",
            "Data Science"
          ],
          "link": ""
        },
        {
          "title": "Online Data Analyst (m,f,d) - Germany",
          "company": "Unknown Company",
          "skills": [
            "A/B Testing",
            "Teams",
            "Data Science"
          ],
          "link": ""
        },
        {
          "title": "Senior Analytics Engineer - Data Generalist (all genders)",
          "company": "Unknown Company",
          "skills": [
            "A/B Testing",
            "Teams",
            "Data Science"
          ],
          "link": ""
        },
        {
          "title": "Data Analyst (Gaming) (f/m/d)",
          "company": "Unknown Company",
          "skills": [
            "A/B Testing",
            "Teams",
            "Data Science"
          ],
          "link": ""
        },
        {
          "title": "Service Innovation & Strategy - Retain Analytics Product Owner (m/f/d)",
          "company": "Unknown Company",
          "skills": [
            "A/B Testing",
            "Teams",
            "Data Science"
          ],
          "link": ""
        },
        {
          "title": "Data Analyst",
          "company": "Unknown Company",
          "skills": [
            "A/B Testing",
            "Teams",
            "Data Science"
          ],
          "link": ""
        },
        {
          "title": "Senior Analytics Engineer - Data Generalist (all genders)",
          "company": "Unknown Company",
          "skills": [
            "A/B Testing",
            "Teams",
            "Data Science"
          ],
          "link": ""
        },
        {
          "title": "Cloud and Data Platform Engineering Lead",
          "company": "Unknown Company",
          "skills": [
            "A/B Testing",
            "Teams",
            "Data Science"
          ],
          "link": ""
        },
        {
          "title": "KYC Analyst - Temporary position",
          "company": "Unknown Company",
          "skills": [
            "A/B Testing",
            "Teams",
            "Data Science"
          ],
          "link": ""
        },
        {
          "title": "European High Yield Credit Analyst - Remote",
          "company": "Unknown Company",
          "skills": [
            "A/B Testing",
            "Teams",
            "Data Science"
          ],
          "link": ""
        },
        {
          "title": "Analytics Engineer (m|w|d) im Bereich Business Intelligence & Web Analytics",
          "company": "Unknown Company",
          "skills": [
            "A/B Testing",
            "Teams",
            "Data Science"
          ],
          "link": ""
        },
        {
          "title": "(Junior) Data Analyst (m/w/d)",
          "company": "Unknown Company",
          "skills": [
            "A/B Testing",
            "Teams",
            "Data Science"
          ],
          "link": ""
        },
        {
          "title": "Trainee (m/w/d) zum SAP Cloud Consultant",
          "company": "Unknown Company",
          "skills": [
            "A/B Testing",
            "Teams",
            "Data Science"
          ],
          "link": ""
        },
        {
          "title": "Data Analyst (w/m/d) f\u00fcr MES und Batch Systeme in der Kosmetik- und Pharmaindustrie",
          "company": "Unknown Company",
          "skills": [
            "A/B Testing",
            "Teams",
            "Data Science"
          ],
          "link": ""
        },
        {
          "title": "BI & Data Operations Analyst (m/w/d) im Bereich Digital Health",
          "company": "Unknown Company",
          "skills": [
            "A/B Testing",
            "Teams",
            "Data Science"
          ],
          "link": ""
        },
        {
          "title": "Data Analyst/Consultant - Fokus Power BI (m/w/d)",
          "company": "Unknown Company",
          "skills": [
            "A/B Testing",
            "Teams",
            "Data Science"
          ],
          "link": ""
        },
        {
          "title": "Trainee (m/w/d) zum SAP Cloud Consultant",
          "company": "Unknown Company",
          "skills": [
            "A/B Testing",
            "Teams",
            "Data Science"
          ],
          "link": ""
        }
      ]
    }
  },
  "last_updated": "2025-04-25T23:27:35Z"
}